aliyunsdkpaielasticdatasetaccelerator/__init__.py
aliyunsdkpaielasticdatasetaccelerator/request/__init__.py
aliyunsdkpaielasticdatasetaccelerator/request/v20220801/BindEndpointRequest.py
aliyunsdkpaielasticdatasetaccelerator/request/v20220801/CreateEndpointRequest.py
aliyunsdkpaielasticdatasetaccelerator/request/v20220801/CreateInstanceRequest.py
aliyunsdkpaielasticdatasetaccelerator/request/v20220801/CreateSlotRequest.py
aliyunsdkpaielasticdatasetaccelerator/request/v20220801/CreateTagRequest.py
aliyunsdkpaielasticdatasetaccelerator/request/v20220801/DeleteEndpointRequest.py
aliyunsdkpaielasticdatasetaccelerator/request/v20220801/DeleteInstanceRequest.py
aliyunsdkpaielasticdatasetaccelerator/request/v20220801/DeleteSlotRequest.py
aliyunsdkpaielasticdatasetaccelerator/request/v20220801/DeleteTagRequest.py
aliyunsdkpaielasticdatasetaccelerator/request/v20220801/DescribeComponentRequest.py
aliyunsdkpaielasticdatasetaccelerator/request/v20220801/DescribeEndpointRequest.py
aliyunsdkpaielasticdatasetaccelerator/request/v20220801/DescribeInstanceRequest.py
aliyunsdkpaielasticdatasetaccelerator/request/v20220801/DescribeSlotRequest.py
aliyunsdkpaielasticdatasetaccelerator/request/v20220801/ListComponentsRequest.py
aliyunsdkpaielasticdatasetaccelerator/request/v20220801/ListEndpointsRequest.py
aliyunsdkpaielasticdatasetaccelerator/request/v20220801/ListInstancesRequest.py
aliyunsdkpaielasticdatasetaccelerator/request/v20220801/ListSlotsRequest.py
aliyunsdkpaielasticdatasetaccelerator/request/v20220801/ListTagsRequest.py
aliyunsdkpaielasticdatasetaccelerator/request/v20220801/QueryInstanceMetricsRequest.py
aliyunsdkpaielasticdatasetaccelerator/request/v20220801/QuerySlotMetricsRequest.py
aliyunsdkpaielasticdatasetaccelerator/request/v20220801/QueryStatisticRequest.py
aliyunsdkpaielasticdatasetaccelerator/request/v20220801/StopSlotRequest.py
aliyunsdkpaielasticdatasetaccelerator/request/v20220801/UnbindEndpointRequest.py
aliyun_python_sdk_paielasticdatasetaccelerator-1.0.3.dist-info/LICENSE
aliyun_python_sdk_paielasticdatasetaccelerator-1.0.3.dist-info/METADATA
aliyun_python_sdk_paielasticdatasetaccelerator-1.0.3.dist-info/WHEEL
aliyun_python_sdk_paielasticdatasetaccelerator-1.0.3.dist-info/top_level.txt
aliyun_python_sdk_paielasticdatasetaccelerator-1.0.3.dist-info/RECORD
